genserver/__init__.py
genserver/core.py
genserver/exceptions.py
genserver/typing.py
genserver-0.2.7.dist-info/LICENSE
genserver-0.2.7.dist-info/METADATA
genserver-0.2.7.dist-info/WHEEL
genserver-0.2.7.dist-info/top_level.txt
genserver-0.2.7.dist-info/RECORD
